{"title":"Combined feed","url":"https://zyzcfzs.github.io/feeds/all.xml","elements":[{"title":"妖精的尾巴 百年任务 (看漫画)","contents":"<a class=\"bcover\" href=\"/comic/28905/\" title=\"妖精的尾巴 百年任务\"><img src=\"//cf.mhgui.com/cpic/b/28905.jpg\" alt=\"妖精的尾巴 百年任务\"><span class=\"bg\"></span><span class=\"tt\">更新至第165话 五只妖精</span><span class=\"sl\"></span></a><p class=\"ell\"><a href=\"/comic/28905/\" title=\"妖精的尾巴 百年任务\">妖精的尾巴 百年任务</a></p><span class=\"updateon\">更新于：2024-08-08<em>9.1</em></span>","link":"https://www.manhuagui.com/comic/28905/","retrieved":1723090703706},{"title":"WIND BREAKER (看漫画)","contents":"<a class=\"bcover\" href=\"/comic/41632/\" title=\"WIND BREAKER\"><img src=\"//cf.mhgui.com/cpic/b/41632.jpg\" alt=\"WIND BREAKER\"><span class=\"bg\"></span><span class=\"tt\">更新至第150话</span><span class=\"sl\"></span></a><p class=\"ell\"><a href=\"/comic/41632/\" title=\"WIND BREAKER\">WIND BREAKER</a></p><span class=\"updateon\">更新于：2024-08-08<em>9.0</em></span>","link":"https://www.manhuagui.com/comic/41632/","retrieved":1723090703706},{"title":"世界上最高傲的王妃维多利亚・维娜・乌修仁 (看漫画)","contents":"<a class=\"bcover\" href=\"/comic/42251/\" title=\"世界上最高傲的王妃维多利亚・维娜・乌修仁\"><img src=\"//cf.mhgui.com/cpic/b/42251.jpg\" alt=\"世界上最高傲的王妃维多利亚・维娜・乌修仁\"><span class=\"bg\"></span><span class=\"tt\">更新至四格漫画40</span><span class=\"sl\"></span></a><p class=\"ell\"><a href=\"/comic/42251/\" title=\"世界上最高傲的王妃维多利亚・维娜・乌修仁\">世界上最高傲的王妃维多利亚・维娜・乌修仁</a></p><span class=\"updateon\">更新于：2024-08-08<em>9.4</em></span>","link":"https://www.manhuagui.com/comic/42251/","retrieved":1723090703706},{"title":"杜鹃的婚约 (看漫画)","contents":"<a class=\"bcover\" href=\"/comic/33643/\" title=\"杜鹃的婚约\"><img src=\"//cf.mhgui.com/cpic/b/33643.jpg\" alt=\"杜鹃的婚约\"><span class=\"bg\"></span><span class=\"tt\">更新至第215话[完]</span><span class=\"fd\"></span></a><p class=\"ell\"><a href=\"/comic/33643/\" title=\"杜鹃的婚约\">杜鹃的婚约</a></p><span class=\"updateon\">更新于：2024-08-08<em>8.3</em></span>","link":"https://www.manhuagui.com/comic/33643/","retrieved":1723090703707},{"title":"在魔王城说晚安 (看漫画)","contents":"<a class=\"bcover\" href=\"/comic/20345/\" title=\"在魔王城说晚安\"><img src=\"//cf.mhgui.com/cpic/b/20345_04.jpg\" alt=\"在魔王城说晚安\"><span class=\"bg\"></span><span class=\"tt\">更新至第372话</span><span class=\"sl\"></span></a><p class=\"ell\"><a href=\"/comic/20345/\" title=\"在魔王城说晚安\">在魔王城说晚安</a></p><span class=\"updateon\">更新于：2024-08-08<em>9.2</em></span>","link":"https://www.manhuagui.com/comic/20345/","retrieved":1723090703708},{"title":"古见同学是沟通鲁蛇。 (看漫画)","contents":"<a class=\"bcover\" href=\"/comic/18369/\" title=\"古见同学是沟通鲁蛇。\"><img src=\"//cf.mhgui.com/cpic/b/18369_83.jpg\" alt=\"古见同学是沟通鲁蛇。\"><span class=\"bg\"></span><span class=\"tt\">更新至第477话</span><span class=\"sl\"></span></a><p class=\"ell\"><a href=\"/comic/18369/\" title=\"古见同学是沟通鲁蛇。\">古见同学是沟通鲁蛇。</a></p><span class=\"updateon\">更新于：2024-08-08<em>9.1</em></span>","link":"https://www.manhuagui.com/comic/18369/","retrieved":1723090703709},{"title":"这便是我的决胜服 (看漫画)","contents":"<a class=\"bcover\" href=\"/comic/53339/\" title=\"这便是我的决胜服\"><img src=\"//cf.mhgui.com/cpic/b/53339.jpg\" alt=\"这便是我的决胜服\"><span class=\"bg\"></span><span class=\"tt\">更新至短篇[完]</span><span class=\"fd\"></span></a><p class=\"ell\"><a href=\"/comic/53339/\" title=\"这便是我的决胜服\">这便是我的决胜服</a></p><span class=\"updateon\">更新于：2024-08-08<em>7.3</em></span>","link":"https://www.manhuagui.com/comic/53339/","retrieved":1723090703709},{"title":"胜利的女神：NIKKE 甜蜜日常 (看漫画)","contents":"<a class=\"bcover\" href=\"/comic/50538/\" title=\"胜利的女神：NIKKE 甜蜜日常\"><img src=\"//cf.mhgui.com/cpic/b/50538.jpg\" alt=\"胜利的女神：NIKKE 甜蜜日常\"><span class=\"bg\"></span><span class=\"tt\">更新至第09话</span><span class=\"sl\"></span></a><p class=\"ell\"><a href=\"/comic/50538/\" title=\"胜利的女神：NIKKE 甜蜜日常\">胜利的女神：NIKKE 甜蜜日常</a></p><span class=\"updateon\">更新于：2024-08-08<em>6.6</em></span>","link":"https://www.manhuagui.com/comic/50538/","retrieved":1723090703710},{"title":"白馒头做了人类灭绝的梦 (看漫画)","contents":"<a class=\"bcover\" href=\"/comic/28560/\" title=\"白馒头做了人类灭绝的梦\"><img src=\"//cf.mhgui.com/cpic/b/28560.jpg\" alt=\"白馒头做了人类灭绝的梦\"><span class=\"bg\"></span><span class=\"tt\">更新至re85</span><span class=\"sl\"></span></a><p class=\"ell\"><a href=\"/comic/28560/\" title=\"白馒头做了人类灭绝的梦\">白馒头做了人类灭绝的梦</a></p><span class=\"updateon\">更新于：2024-08-08<em>4.2</em></span>","link":"https://www.manhuagui.com/comic/28560/","retrieved":1723090703710},{"title":"凸起吧！男娘主播！ (看漫画)","contents":"<a class=\"bcover\" href=\"/comic/53189/\" title=\"凸起吧！男娘主播！\"><img src=\"//cf.mhgui.com/cpic/b/53189.jpg\" alt=\"凸起吧！男娘主播！\"><span class=\"bg\"></span><span class=\"tt\">更新至街头采访</span><span class=\"sl\"></span></a><p class=\"ell\"><a href=\"/comic/53189/\" title=\"凸起吧！男娘主播！\">凸起吧！男娘主播！</a></p><span class=\"updateon\">更新于：2024-08-08<em>3.8</em></span>","link":"https://www.manhuagui.com/comic/53189/","retrieved":1723047397055},{"title":"伴君身旁(C102) (看漫画)","contents":"<a class=\"bcover\" href=\"/comic/53338/\" title=\"伴君身旁(C102)\"><img src=\"//cf.mhgui.com/cpic/b/53338.jpg\" alt=\"伴君身旁(C102)\"><span class=\"bg\"></span><span class=\"tt\">更新至全一卷[完]</span><span class=\"fd\"></span></a><p class=\"ell\"><a href=\"/comic/53338/\" title=\"伴君身旁(C102)\">伴君身旁(C102)</a></p><span class=\"updateon\">更新于：2024-08-08<em>8.0</em></span>","link":"https://www.manhuagui.com/comic/53338/","retrieved":1723090703710},{"title":"兄与妹的特别行动 (看漫画)","contents":"<a class=\"bcover\" href=\"/comic/53337/\" title=\"兄与妹的特别行动\"><img src=\"//cf.mhgui.com/cpic/b/53337.jpg\" alt=\"兄与妹的特别行动\"><span class=\"bg\"></span><span class=\"tt\">更新至全一卷[完]</span><span class=\"fd\"></span></a><p class=\"ell\"><a href=\"/comic/53337/\" title=\"兄与妹的特别行动\">兄与妹的特别行动</a></p><span class=\"updateon\">更新于：2024-08-08<em>0.0</em></span>","link":"https://www.manhuagui.com/comic/53337/","retrieved":1723090703712},{"title":"闪耀情结 (看漫画)","contents":"<a class=\"bcover\" href=\"/comic/53336/\" title=\"闪耀情结\"><img data-src=\"//cf.mhgui.com/cpic/b/53336.jpg\" alt=\"闪耀情结\"><span class=\"bg\"></span><span class=\"tt\">更新至全一话[完]</span><span class=\"fd\"></span></a><p class=\"ell\"><a href=\"/comic/53336/\" title=\"闪耀情结\">闪耀情结</a></p><span class=\"updateon\">更新于：2024-08-08<em>10.0</em></span>","link":"https://www.manhuagui.com/comic/53336/","retrieved":1723090703713},{"title":"不思议游戏 白虎仙记 (看漫画)","contents":"<a class=\"bcover\" href=\"/comic/25367/\" title=\"不思议游戏 白虎仙记\"><img data-src=\"//cf.mhgui.com/cpic/b/25367.jpg\" alt=\"不思议游戏 白虎仙记\"><span class=\"bg\"></span><span class=\"tt\">更新至番外01</span><span class=\"sl\"></span></a><p class=\"ell\"><a href=\"/comic/25367/\" title=\"不思议游戏 白虎仙记\">不思议游戏 白虎仙记</a></p><span class=\"updateon\">更新于：2024-08-08<em>9.2</em></span>","link":"https://www.manhuagui.com/comic/25367/","retrieved":1723090703722},{"title":"颤栗诊所 (看漫画)","contents":"<a class=\"bcover\" href=\"/comic/34275/\" title=\"颤栗诊所\"><img data-src=\"//cf.mhgui.com/cpic/b/34275.jpg\" alt=\"颤栗诊所\"><span class=\"bg\"></span><span class=\"tt\">更新至S2-41</span><span class=\"sl\"></span></a><p class=\"ell\"><a href=\"/comic/34275/\" title=\"颤栗诊所\">颤栗诊所</a></p><span class=\"updateon\">更新于：2024-08-08<em>8.0</em></span>","link":"https://www.manhuagui.com/comic/34275/","retrieved":1723090703722},{"title":"恐龙与河童的图书室 (看漫画)","contents":"<a class=\"bcover\" href=\"/comic/52523/\" title=\"恐龙与河童的图书室\"><img data-src=\"//cf.mhgui.com/cpic/b/52523.jpg\" alt=\"恐龙与河童的图书室\"><span class=\"bg\"></span><span class=\"tt\">更新至第11话</span><span class=\"sl\"></span></a><p class=\"ell\"><a href=\"/comic/52523/\" title=\"恐龙与河童的图书室\">恐龙与河童的图书室</a></p><span class=\"updateon\">更新于：2024-08-08<em>7.3</em></span>","link":"https://www.manhuagui.com/comic/52523/","retrieved":1723090703722},{"title":"野槌蛇与海风 (看漫画)","contents":"<a class=\"bcover\" href=\"/comic/53203/\" title=\"野槌蛇与海风\"><img data-src=\"//cf.mhgui.com/cpic/b/53203.jpg\" alt=\"野槌蛇与海风\"><span class=\"bg\"></span><span class=\"tt\">更新至第03话</span><span class=\"sl\"></span></a><p class=\"ell\"><a href=\"/comic/53203/\" title=\"野槌蛇与海风\">野槌蛇与海风</a></p><span class=\"updateon\">更新于：2024-08-08<em>9.5</em></span>","link":"https://www.manhuagui.com/comic/53203/","retrieved":1723090703730},{"title":"青春期笨蛋不做怀梦美少女的梦 (看漫画)","contents":"<a class=\"bcover\" href=\"/comic/48258/\" title=\"青春期笨蛋不做怀梦美少女的梦\"><img data-src=\"//cf.mhgui.com/cpic/b/48258.jpg\" alt=\"青春期笨蛋不做怀梦美少女的梦\"><span class=\"bg\"></span><span class=\"tt\">更新至短篇小说</span><span class=\"sl\"></span></a><p class=\"ell\"><a href=\"/comic/48258/\" title=\"青春期笨蛋不做怀梦美少女的梦\">青春期笨蛋不做怀梦美少女的梦</a></p><span class=\"updateon\">更新于：2024-08-08<em>9.4</em></span>","link":"https://www.manhuagui.com/comic/48258/","retrieved":1723090703731},{"title":"我才不想当女孩子！ (看漫画)","contents":"<a class=\"bcover\" href=\"/comic/52360/\" title=\"我才不想当女孩子！\"><img data-src=\"//cf.mhgui.com/cpic/b/52360.jpg\" alt=\"我才不想当女孩子！\"><span class=\"bg\"></span><span class=\"tt\">更新至番外篇</span><span class=\"sl\"></span></a><p class=\"ell\"><a href=\"/comic/52360/\" title=\"我才不想当女孩子！\">我才不想当女孩子！</a></p><span class=\"updateon\">更新于：2024-08-08<em>9.2</em></span>","link":"https://www.manhuagui.com/comic/52360/","retrieved":1723090703731},{"title":"妇～妇 (看漫画)","contents":"<a class=\"bcover\" href=\"/comic/53335/\" title=\"妇～妇\"><img data-src=\"//cf.mhgui.com/cpic/b/53335.jpg\" alt=\"妇～妇\"><span class=\"bg\"></span><span class=\"tt\">更新至10th anniversary 第1回[完]</span><span class=\"fd\"></span></a><p class=\"ell\"><a href=\"/comic/53335/\" title=\"妇～妇\">妇～妇</a></p><span class=\"updateon\">更新于：2024-08-08<em>10.0</em></span>","link":"https://www.manhuagui.com/comic/53335/","retrieved":1723090703744},{"title":"池水尽红 (看漫画)","contents":"<a class=\"bcover\" href=\"/comic/52727/\" title=\"池水尽红\"><img data-src=\"//cf.mhgui.com/cpic/b/52727.jpg\" alt=\"池水尽红\"><span class=\"bg\"></span><span class=\"tt\">更新至第04话</span><span class=\"sl\"></span></a><p class=\"ell\"><a href=\"/comic/52727/\" title=\"池水尽红\">池水尽红</a></p><span class=\"updateon\">更新于：2024-08-08<em>4.7</em></span>","link":"https://www.manhuagui.com/comic/52727/","retrieved":1723090703744},{"title":"午夜心旋律 (看漫画)","contents":"<a class=\"bcover\" href=\"/comic/49749/\" title=\"午夜心旋律\"><img data-src=\"//cf.mhgui.com/cpic/b/49749.jpg\" alt=\"午夜心旋律\"><span class=\"bg\"></span><span class=\"tt\">更新至第42话</span><span class=\"sl\"></span></a><p class=\"ell\"><a href=\"/comic/49749/\" title=\"午夜心旋律\">午夜心旋律</a></p><span class=\"updateon\">更新于：2024-08-08<em>9.4</em></span>","link":"https://www.manhuagui.com/comic/49749/","retrieved":1723090703744},{"title":"魔女魔女S-WITCH (看漫画)","contents":"<a class=\"bcover\" href=\"/comic/52409/\" title=\"魔女魔女S-WITCH\"><img data-src=\"//cf.mhgui.com/cpic/b/52409.jpg\" alt=\"魔女魔女S-WITCH\"><span class=\"bg\"></span><span class=\"tt\">更新至第03话</span><span class=\"sl\"></span></a><p class=\"ell\"><a href=\"/comic/52409/\" title=\"魔女魔女S-WITCH\">魔女魔女S-WITCH</a></p><span class=\"updateon\">更新于：2024-08-08<em>7.2</em></span>","link":"https://www.manhuagui.com/comic/52409/","retrieved":1723090703744},{"title":"初恋与濒死转生女神 (看漫画)","contents":"<a class=\"bcover\" href=\"/comic/51165/\" title=\"初恋与濒死转生女神\"><img data-src=\"//cf.mhgui.com/cpic/b/51165.jpg\" alt=\"初恋与濒死转生女神\"><span class=\"bg\"></span><span class=\"tt\">更新至第26话</span><span class=\"sl\"></span></a><p class=\"ell\"><a href=\"/comic/51165/\" title=\"初恋与濒死转生女神\">初恋与濒死转生女神</a></p><span class=\"updateon\">更新于：2024-08-08<em>9.1</em></span>","link":"https://www.manhuagui.com/comic/51165/","retrieved":1723090703745},{"title":"今宵女仆无法痛下杀手 (看漫画)","contents":"<a class=\"bcover\" href=\"/comic/50055/\" title=\"今宵女仆无法痛下杀手\"><img data-src=\"//cf.mhgui.com/cpic/b/50055.jpg\" alt=\"今宵女仆无法痛下杀手\"><span class=\"bg\"></span><span class=\"tt\">更新至第08话</span><span class=\"sl\"></span></a><p class=\"ell\"><a href=\"/comic/50055/\" title=\"今宵女仆无法痛下杀手\">今宵女仆无法痛下杀手</a></p><span class=\"updateon\">更新于：2024-08-08<em>9.0</em></span>","link":"https://www.manhuagui.com/comic/50055/","retrieved":1723090703746},{"title":"情书与13岁女演员 (看漫画)","contents":"<a class=\"bcover\" href=\"/comic/45963/\" title=\"情书与13岁女演员\"><img data-src=\"//cf.mhgui.com/cpic/b/45963.jpg\" alt=\"情书与13岁女演员\"><span class=\"bg\"></span><span class=\"tt\">更新至第24话</span><span class=\"sl\"></span></a><p class=\"ell\"><a href=\"/comic/45963/\" title=\"情书与13岁女演员\">情书与13岁女演员</a></p><span class=\"updateon\">更新于：2024-08-08<em>9.3</em></span>","link":"https://www.manhuagui.com/comic/45963/","retrieved":1723090703749},{"title":"妖猫阿鼓的人间调查实录 (看漫画)","contents":"<a class=\"bcover\" href=\"/comic/52375/\" title=\"妖猫阿鼓的人间调查实录\"><img data-src=\"//cf.mhgui.com/cpic/b/52375.jpg\" alt=\"妖猫阿鼓的人间调查实录\"><span class=\"bg\"></span><span class=\"tt\">更新至第06话</span><span class=\"sl\"></span></a><p class=\"ell\"><a href=\"/comic/52375/\" title=\"妖猫阿鼓的人间调查实录\">妖猫阿鼓的人间调查实录</a></p><span class=\"updateon\">更新于：2024-08-08<em>9.5</em></span>","link":"https://www.manhuagui.com/comic/52375/","retrieved":1723090703749},{"title":"黑魔法宿舍的三恶人 (看漫画)","contents":"<a class=\"bcover\" href=\"/comic/53334/\" title=\"黑魔法宿舍的三恶人\"><img data-src=\"//cf.mhgui.com/cpic/b/53334.jpg\" alt=\"黑魔法宿舍的三恶人\"><span class=\"bg\"></span><span class=\"tt\">更新至第01话</span><span class=\"sl\"></span></a><p class=\"ell\"><a href=\"/comic/53334/\" title=\"黑魔法宿舍的三恶人\">黑魔法宿舍的三恶人</a></p><span class=\"updateon\">更新于：2024-08-08<em>9.8</em></span>","link":"https://www.manhuagui.com/comic/53334/","retrieved":1723090703749},{"title":"超超超超喜欢你的一百个女孩子 (看漫画)","contents":"<a class=\"bcover\" href=\"/comic/34816/\" title=\"超超超超喜欢你的一百个女孩子\"><img data-src=\"//cf.mhgui.com/cpic/b/34816.jpg\" alt=\"超超超超喜欢你的一百个女孩子\"><span class=\"bg\"></span><span class=\"tt\">更新至第186话</span><span class=\"sl\"></span></a><p class=\"ell\"><a href=\"/comic/34816/\" title=\"超超超超喜欢你的一百个女孩子\">超超超超喜欢你的一百个女孩子</a></p><span class=\"updateon\">更新于：2024-08-08<em>9.2</em></span>","link":"https://www.manhuagui.com/comic/34816/","retrieved":1723090703750},{"title":"濑文丽步的奇闻异事 (看漫画)","contents":"<a class=\"bcover\" href=\"/comic/42548/\" title=\"濑文丽步的奇闻异事\"><img data-src=\"//cf.mhgui.com/cpic/b/42548.jpg\" alt=\"濑文丽步的奇闻异事\"><span class=\"bg\"></span><span class=\"tt\">更新至第09话</span><span class=\"sl\"></span></a><p class=\"ell\"><a href=\"/comic/42548/\" title=\"濑文丽步的奇闻异事\">濑文丽步的奇闻异事</a></p><span class=\"updateon\">更新于：2024-08-08<em>8.9</em></span>","link":"https://www.manhuagui.com/comic/42548/","retrieved":1723090703750},{"title":"魔女的花屋 (看漫画)","contents":"<a class=\"bcover\" href=\"/comic/51005/\" title=\"魔女的花屋\"><img data-src=\"//cf.mhgui.com/cpic/b/51005.jpg\" alt=\"魔女的花屋\"><span class=\"bg\"></span><span class=\"tt\">更新至第08话</span><span class=\"sl\"></span></a><p class=\"ell\"><a href=\"/comic/51005/\" title=\"魔女的花屋\">魔女的花屋</a></p><span class=\"updateon\">更新于：2024-08-08<em>9.1</em></span>","link":"https://www.manhuagui.com/comic/51005/","retrieved":1723090703752},{"title":"双子菜园 (看漫画)","contents":"<a class=\"bcover\" href=\"/comic/50042/\" title=\"双子菜园\"><img data-src=\"//cf.mhgui.com/cpic/b/50042.jpg\" alt=\"双子菜园\"><span class=\"bg\"></span><span class=\"tt\">更新至第10话</span><span class=\"sl\"></span></a><p class=\"ell\"><a href=\"/comic/50042/\" title=\"双子菜园\">双子菜园</a></p><span class=\"updateon\">更新于：2024-08-08<em>8.9</em></span>","link":"https://www.manhuagui.com/comic/50042/","retrieved":1723090703753},{"title":"弱气MAX的大小姐、居然接受了铁腕未婚夫的赌约 (看漫画)","contents":"<a class=\"bcover\" href=\"/comic/39336/\" title=\"弱气MAX的大小姐、居然接受了铁腕未婚夫的赌约\"><img data-src=\"//cf.mhgui.com/cpic/b/39336.jpg\" alt=\"弱气MAX的大小姐、居然接受了铁腕未婚夫的赌约\"><span class=\"bg\"></span><span class=\"tt\">更新至第03卷</span><span class=\"sl\"></span></a><p class=\"ell\"><a href=\"/comic/39336/\" title=\"弱气MAX的大小姐、居然接受了铁腕未婚夫的赌约\">弱气MAX的大小姐、居然接受了铁腕未婚夫的赌约</a></p><span class=\"updateon\">更新于：2024-08-08<em>9.3</em></span>","link":"https://www.manhuagui.com/comic/39336/","retrieved":1723090703755},{"title":"未踏之地 (看漫画)","contents":"<a class=\"bcover\" href=\"/comic/16759/\" title=\"未踏之地\"><img data-src=\"//cf.mhgui.com/cpic/b/16759.jpg\" alt=\"未踏之地\"><span class=\"bg\"></span><span class=\"tt\">更新至第70话</span><span class=\"sl\"></span></a><p class=\"ell\"><a href=\"/comic/16759/\" title=\"未踏之地\">未踏之地</a></p><span class=\"updateon\">更新于：2024-08-08<em>9.4</em></span>","link":"https://www.manhuagui.com/comic/16759/","retrieved":1723090703756},{"title":"掠夺者剥夺者 (看漫画)","contents":"<a class=\"bcover\" href=\"/comic/53307/\" title=\"掠夺者剥夺者\"><img data-src=\"//cf.mhgui.com/cpic/b/53307.jpg\" alt=\"掠夺者剥夺者\"><span class=\"bg\"></span><span class=\"tt\">更新至第02话</span><span class=\"sl\"></span></a><p class=\"ell\"><a href=\"/comic/53307/\" title=\"掠夺者剥夺者\">掠夺者剥夺者</a></p><span class=\"updateon\">更新于：2024-08-08<em>9.8</em></span>","link":"https://www.manhuagui.com/comic/53307/","retrieved":1723090703757},{"title":"轮回的花瓣 (看漫画)","contents":"<a class=\"bcover\" href=\"/comic/13677/\" title=\"轮回的花瓣\"><img data-src=\"//cf.mhgui.com/cpic/b/13677.jpg\" alt=\"轮回的花瓣\"><span class=\"bg\"></span><span class=\"tt\">更新至第92话</span><span class=\"sl\"></span></a><p class=\"ell\"><a href=\"/comic/13677/\" title=\"轮回的花瓣\">轮回的花瓣</a></p><span class=\"updateon\">更新于：2024-08-08<em>9.0</em></span>","link":"https://www.manhuagui.com/comic/13677/","retrieved":1723090703759},{"title":"金装的维尔梅 (看漫画)","contents":"<a class=\"bcover\" href=\"/comic/27235/\" title=\"金装的维尔梅\"><img data-src=\"//cf.mhgui.com/cpic/b/27235.jpg\" alt=\"金装的维尔梅\"><span class=\"bg\"></span><span class=\"tt\">更新至第24话后篇[完]</span><span class=\"fd\"></span></a><p class=\"ell\"><a href=\"/comic/27235/\" title=\"金装的维尔梅\">金装的维尔梅</a></p><span class=\"updateon\">更新于：2024-08-08<em>8.7</em></span>","link":"https://www.manhuagui.com/comic/27235/","retrieved":1723090703760},{"title":"兔用心棒V4 (看漫画)","contents":"<a class=\"bcover\" href=\"/comic/47291/\" title=\"兔用心棒V4\"><img data-src=\"//cf.mhgui.com/cpic/b/47291.jpg\" alt=\"兔用心棒V4\"><span class=\"bg\"></span><span class=\"tt\">更新至第278卷</span><span class=\"sl\"></span></a><p class=\"ell\"><a href=\"/comic/47291/\" title=\"兔用心棒V4\">兔用心棒V4</a></p><span class=\"updateon\">更新于：2024-08-08<em>4.5</em></span>","link":"https://www.manhuagui.com/comic/47291/","retrieved":1723090703761},{"title":"对不起了人类！！～蹂躏觉醒的开幕 (看漫画)","contents":"<a class=\"bcover\" href=\"/comic/53333/\" title=\"对不起了人类！！～蹂躏觉醒的开幕\"><img data-src=\"//cf.mhgui.com/cpic/b/53333.jpg\" alt=\"对不起了人类！！～蹂躏觉醒的开幕\"><span class=\"bg\"></span><span class=\"tt\">更新至短篇[完]</span><span class=\"fd\"></span></a><p class=\"ell\"><a href=\"/comic/53333/\" title=\"对不起了人类！！～蹂躏觉醒的开幕\">对不起了人类！！～蹂躏觉醒的开幕</a></p><span class=\"updateon\">更新于：2024-08-08<em>6.0</em></span>","link":"https://www.manhuagui.com/comic/53333/","retrieved":1723090703762},{"title":"爆进、大小姐之道 (看漫画)","contents":"<a class=\"bcover\" href=\"/comic/53310/\" title=\"爆进、大小姐之道\"><img data-src=\"//cf.mhgui.com/cpic/b/53310.jpg\" alt=\"爆进、大小姐之道\"><span class=\"bg\"></span><span class=\"tt\">更新至第02话</span><span class=\"sl\"></span></a><p class=\"ell\"><a href=\"/comic/53310/\" title=\"爆进、大小姐之道\">爆进、大小姐之道</a></p><span class=\"updateon\">更新于：2024-08-08<em>6.7</em></span>","link":"https://www.manhuagui.com/comic/53310/","retrieved":1723090703764},{"title":"这片难绷的大陆 (看漫画)","contents":"<a class=\"bcover\" href=\"/comic/50197/\" title=\"这片难绷的大陆\"><img data-src=\"//cf.mhgui.com/cpic/b/50197.jpg\" alt=\"这片难绷的大陆\"><span class=\"bg\"></span><span class=\"tt\">更新至第20话</span><span class=\"sl\"></span></a><p class=\"ell\"><a href=\"/comic/50197/\" title=\"这片难绷的大陆\">这片难绷的大陆</a></p><span class=\"updateon\">更新于：2024-08-08<em>9.1</em></span>","link":"https://www.manhuagui.com/comic/50197/","retrieved":1723090703765},{"title":"男子高中生的异世界jk转生 (看漫画)","contents":"<a class=\"bcover\" href=\"/comic/48800/\" title=\"男子高中生的异世界jk转生\"><img data-src=\"//cf.mhgui.com/cpic/b/48800.jpg\" alt=\"男子高中生的异世界jk转生\"><span class=\"bg\"></span><span class=\"tt\">更新至第06话</span><span class=\"sl\"></span></a><p class=\"ell\"><a href=\"/comic/48800/\" title=\"男子高中生的异世界jk转生\">男子高中生的异世界jk转生</a></p><span class=\"updateon\">更新于：2024-08-08<em>8.1</em></span>","link":"https://www.manhuagui.com/comic/48800/","retrieved":1723090703767},{"title":"捌月 08 星期四 宜   奋发 (电影日历)","contents":"<a id=\"movie-img-a\" href=\"/mov/681306401227253/\" target=\"_blank\">\n                        <div id=\"movie-img-box\">\n                            <div id=\"movie-img-fixed\">查看详情</div>\n                            <img id=\"movie-img\" src=\"/uploads/movimg/523/107d/681306401227253.webp\" alt=\"\">\n                        </div>\n                    </a>\n                    <a id=\"movie-information\" href=\"/mov/681306401227253/?>\" target=\"_blank\">7.8分&nbsp;喜剧/动作/惊悚&nbsp;2022&nbsp;美国</a>\n                    \n                    <span id=\"movie-text\">或许命运这趟列车，不是为了让人降服于命运，而是为了让你了解，过去和现在，是怎样操控着未来，而那些微不足道的小事，又是怎么引来狂风骤雨。</span>\n                    <a id=\"movie-name\" href=\"/mov/681306401227253/\" target=\"_blank\">——《子弹列车》</a>","link":"https://www.cikeee.cc/mov/681306401227253/","retrieved":1723047401037},{"title":"Carles Puigdemont returns to Spain after nearly 7 years as a fugitive (BitToc Hot)","contents":"<img src=\"https://cdn.biztoc.com/f66889cbbdf71414_sq.webp\" class=\"pl\" alt=\"\" style=\"visibility: visible;\">                        Carles Puigdemont returns to Spain after nearly 7 years as a fugitive","link":"https://apnews.com/article/spain-catalonia-carles-puigdemont-returns-d89d88131983da1fdd39b6ddcb85c297?ref=biztoc.com","retrieved":1723105079510},{"title":"State of emergency declared after Ukrainian raid into Russian border region (BitToc Hot)","contents":"<img src=\"https://cdn.biztoc.com/50448175cdc2e403_sq.webp\" class=\"pl\" alt=\"\" style=\"visibility: visible;\">                        State of emergency declared after Ukrainian raid into Russian border region","link":"https://www.cnbc.com/2024/08/08/state-of-emergency-declared-in-kursk-as-ukrainians-and-russians-clash.html?ref=biztoc.com","retrieved":1723105079511},{"title":"Brits warned retweeting riot info could be a criminal offense (BitToc Hot)","contents":"<img src=\"https://cdn.biztoc.com/31b493d6a0ae3f2c_sq.webp\" class=\"pl\" alt=\"\" style=\"visibility: visible;\">                        Brits warned retweeting riot info could be a criminal offense","link":"https://www.zerohedge.com/political/brits-warned-merely-retweeting-information-about-riots-could-be-criminal-offense?ref=biztoc.com","retrieved":1723105079513},{"title":"Kamala Harris open to Israel arms embargo talks (BitToc Hot)","contents":"Kamala Harris open to Israel arms embargo talks","link":"https://www.newsweek.com/kamala-harris-open-israel-arms-embargo-palestine-conflict-1936259?ref=biztoc.com","retrieved":1723105079514},{"title":"Home buyers are rare due to 3 major hurdles (BitToc Hot)","contents":"<img src=\"https://cdn.biztoc.com/b78674cc806c779c_sq.webp\" class=\"pl\" alt=\"\" style=\"visibility: visible;\">                        Home buyers are rare due to 3 major hurdles","link":"https://www.barrons.com/articles/home-buyers-are-rare-breed-3-things-holding-them-back-02bc80b8?ref=biztoc.com","retrieved":1723105079517}]}